esimaccess_python/__init__.py
esimaccess_python/auth.py
esimaccess_python/api/__init__.py
esimaccess_python/api/package.py
esimaccess_python/api/pageparam.py
esimaccess_python-0.1.1.dist-info/METADATA
esimaccess_python-0.1.1.dist-info/WHEEL
esimaccess_python-0.1.1.dist-info/top_level.txt
esimaccess_python-0.1.1.dist-info/RECORD
