Metadata-Version: 2.1
Name: esimaccess-python
Version: 0.1.1
Summary: Python SDK for the Esimaccess API
Author: Corbin Li
Requires-Dist: httpx
